mylib1/__init__.py
mylib1-0.1.dist-info/LICENSE.txt
mylib1-0.1.dist-info/METADATA
mylib1-0.1.dist-info/WHEEL
mylib1-0.1.dist-info/top_level.txt
mylib1-0.1.dist-info/RECORD
